pyromancy/__init__.py
pyromancy/infra.py
pyromancy/utils.py
pyromancy/nodes/__init__.py
pyromancy/nodes/base.py
pyromancy/nodes/gaussian.py
pyromancy/nodes/special.py
pyromancy_ai-0.0.1.dist-info/METADATA
pyromancy_ai-0.0.1.dist-info/WHEEL
pyromancy_ai-0.0.1.dist-info/licenses/LICENSE.txt
pyromancy_ai-0.0.1.dist-info/RECORD
